ja3/__init__.py
ja3/ja3.py
pyja3-1.0.0.dist-info/DESCRIPTION.rst
pyja3-1.0.0.dist-info/METADATA
pyja3-1.0.0.dist-info/RECORD
pyja3-1.0.0.dist-info/WHEEL
pyja3-1.0.0.dist-info/entry_points.txt
pyja3-1.0.0.dist-info/metadata.json
pyja3-1.0.0.dist-info/top_level.txt
