Metadata-Version: 2.0
Name: pyja3
Version: 1.0.0
Summary: Generate JA3 fingerprints from PCAPs using Python.
Home-page: https://github.com/salesforce/ja3
Author: Tommy Stallings
Author-email: tommy.stallings@salesforce.com
License: BSD
Keywords: ja3,fingerprints,defender,ssl,packets
Platform: UNKNOWN
Classifier: Development Status :: 4 - Beta
Classifier: Intended Audience :: End Users/Desktop
Classifier: License :: OSI Approved :: BSD License
Classifier: Natural Language :: English
Classifier: Programming Language :: Python
Classifier: Topic :: Software Development :: Libraries
Requires-Dist: dpkt
